pdm_publish/__init__.py
pdm_publish/command.py
pdm_publish/config.py
pdm_publish/core.py
pdm_publish-0.2.1.dist-info/entry_points.txt
pdm_publish-0.2.1.dist-info/WHEEL
pdm_publish-0.2.1.dist-info/METADATA
pdm_publish-0.2.1.dist-info/RECORD
